mathguru/__init__.py
mathguru-0.1.0.dist-info/METADATA
mathguru-0.1.0.dist-info/WHEEL
mathguru-0.1.0.dist-info/top_level.txt
mathguru-0.1.0.dist-info/RECORD
